gluehome/__init__.py
gluehome/auth.py
gluehome/client.py
gluehome/const.py
gluehome/exceptions.py
gluehome/lock.py
gluehome-0.1.2.dist-info/LICENSE
gluehome-0.1.2.dist-info/METADATA
gluehome-0.1.2.dist-info/WHEEL
gluehome-0.1.2.dist-info/top_level.txt
gluehome-0.1.2.dist-info/RECORD
