Metadata-Version: 2.1
Name: gluehome
Version: 0.1.2
Summary: A Python client for interacting with the Glue Home API.
Author-email: Fredrik Sundqvist <fsundqvist@gmail.com>
Maintainer-email: Fredrik Sundqvist <fsundqvist@gmail.com>
License: MIT License
Project-URL: Homepage, https://github.com/MadSpindel/gluehome-python/
Project-URL: Issues, https://github.com/MadSpindel/gluehome-python/issues
License-File: LICENSE
Requires-Dist: requests
